LICENSE
MANIFEST.in
README.md
setup.cfg
setup.py
pyega3/VERSION
pyega3/__init__.py
pyega3/pyega3.py
pyega3.egg-info/PKG-INFO
pyega3.egg-info/SOURCES.txt
pyega3.egg-info/dependency_links.txt
pyega3.egg-info/entry_points.txt
pyega3.egg-info/requires.txt
pyega3.egg-info/top_level.txt
pyega3/config/default_credential_file.json
pyega3/config/default_server_file.json
pyega3/libs/__init__.py
pyega3/libs/auth_client.py
pyega3/libs/commands.py
pyega3/libs/credentials.py
pyega3/libs/data_client.py
pyega3/libs/data_file.py
pyega3/libs/data_set.py
pyega3/libs/error.py
pyega3/libs/file_format.py
pyega3/libs/pretty_printing.py
pyega3/libs/server_config.py
pyega3/libs/stats.py
pyega3/libs/utils.py
tests/__init__.py
tests/functional/__init__.py
tests/functional/test_display_info.py
tests/functional/test_download.py
tests/functional/test_htsget.py
tests/functional/util.py
tests/unit/__init__.py
tests/unit/conftest.py
tests/unit/mock_data_server.py
tests/unit/test_client_ip.py
tests/unit/test_commands.py
tests/unit/test_credentials.py
tests/unit/test_delete_temporary_files.py
tests/unit/test_download_dataset.py
tests/unit/test_download_file.py
tests/unit/test_download_file_slice.py
tests/unit/test_file_format.py
tests/unit/test_generate_output_filename.py
tests/unit/test_get_file_name_size_md5.py
tests/unit/test_list_datasets.py
tests/unit/test_list_files.py
tests/unit/test_md5.py
tests/unit/test_merge_bin_files.py
tests/unit/test_openid.py
tests/unit/test_pretty_printing.py
tests/unit/test_save_to_with_dataset.py
tests/unit/test_save_to_with_file.py
tests/unit/test_server_config.py
tests/unit/test_verify_output_dir.py