Metadata-Version: 2.1
Name: pyega3
Version: 5.2.0
Summary: EGA python client
Home-page: https://github.com/EGA-archive/ega-download-client
Author: EGA team
Author-email: ega-helpdesk@ebi.ac.uk
License: Apache License, Version 2.0
Keywords: EGA,archive
Classifier: Development Status :: 3 - Alpha
Classifier: Topic :: Scientific/Engineering :: Bio-Informatics
Classifier: License :: OSI Approved :: Apache Software License
Classifier: Programming Language :: Python :: 3.6
Requires-Python: >=3.6
License-File: LICENSE
